helpful_math_funcs/__init__.py
helpful_math_funcs/helpful_math_funcs.py
helpful_math_funcs-0.0.1.dist-info/METADATA
helpful_math_funcs-0.0.1.dist-info/WHEEL
helpful_math_funcs-0.0.1.dist-info/top_level.txt
helpful_math_funcs-0.0.1.dist-info/RECORD
